<?xml version="1.0" encoding="utf-8"?>
<elements>
  <info>
    <name>Quabis's Guide to Chronomancy — Magic Items</name>
    <description>Magic items from Quabis's Guide to Chronomancy.</description>
    <author>Dillan Ackerman (homebrew)</author>

    <update version="1.0.0">
      <file name="qgc-magicitems.xml" url="https://raw.githubusercontent.com/SageZeMage/aurora-quabis-chronomancy/main/qgc-magicitems.xml" />
    </update>
  </info>

  <!--
    Example structure (once we know the items):

    <element name="Hourglass of Frozen Moments" type="Magic Item" source="Quabis's Guide to Chronomancy" id="ID_QGC_MAGIC_ITEM_HOURGLASS_OF_FROZEN_MOMENTS">
      <description>
        <p>Item text...</p>
      </description>
      <sheet>
        <description>
          <p>Short version for the character sheet...</p>
        </description>
      </sheet>
      <setters>
        <set name="rarity">Rare</set>
        <set name="category">Magic Item</set>
        <set name="type">Wondrous Item</set>
      </setters>
    </element>
  -->
</elements>
